zhinst/labber/__init__.py
zhinst/labber/_version.py
zhinst/labber/cli_script.py
zhinst/labber/helper.py
zhinst/labber/code_generator/__init__.py
zhinst/labber/code_generator/drivers.py
zhinst/labber/code_generator/templates/device_template.py.j2
zhinst/labber/driver/base_instrument.py
zhinst/labber/driver/logger.py
zhinst/labber/driver/snapshot_manager.py
zhinst/labber/generator/__init__.py
zhinst/labber/generator/conf.py
zhinst/labber/generator/generator.py
zhinst/labber/generator/helpers.py
zhinst/labber/generator/quants.py
zhinst/labber/resources/settings.json
zhinst/labber/resources/settings_json_schema.json
zhinst/labber/static_drivers/Zurich_Instruments_Waveform_Processor/Zurich_Instruments_Waveform_Processor.ini
zhinst/labber/static_drivers/Zurich_Instruments_Waveform_Processor/Zurich_Instruments_Waveform_Processor.py
zhinst_labber-0.3.3.dist-info/AUTHORS
zhinst_labber-0.3.3.dist-info/LICENSE
zhinst_labber-0.3.3.dist-info/METADATA
zhinst_labber-0.3.3.dist-info/WHEEL
zhinst_labber-0.3.3.dist-info/entry_points.txt
zhinst_labber-0.3.3.dist-info/top_level.txt
zhinst_labber-0.3.3.dist-info/RECORD
