Metadata-Version: 2.1
Name: zhinst-labber
Version: 0.3.3
Summary: Zurich Instruments Labber Driver
Home-page: https://github.com/zhinst/zhinst-labber
Author: Zurich Instrument
Author-email: info@zhinst.com
Project-URL: Bug Tracker, https://github.com/zhinst/zhinst-labber/issues
Classifier: Development Status :: 4 - Beta
Classifier: Programming Language :: Python :: 3.7
Classifier: Programming Language :: Python :: 3.8
Classifier: Programming Language :: Python :: 3.9
Classifier: Programming Language :: Python :: 3.10
Classifier: License :: OSI Approved :: MIT License
Classifier: Operating System :: OS Independent
Classifier: Topic :: Scientific/Engineering
Classifier: Intended Audience :: Science/Research
Requires-Python: >=3.7
License-File: LICENSE
License-File: AUTHORS
Requires-Dist: zhinst-toolkit>=0.3.2
Requires-Dist: numpy>=1.16.5
Requires-Dist: click>=8.0
Requires-Dist: jinja2>=3.0
Requires-Dist: natsort>=8.1
Requires-Dist: black>=22.1
Requires-Dist: autoflake>=1.4
